["#!/bin/bash\nvolume=$(pactl list sinks | grep '^[[:space:]]Volume:' | \\\n         head -n $(( $SINK + 1 )) | tail -n 1 | \\\n         sed -e 's,.* \\([0-9][0-9]*\\)%.*,\\1,')\necho \"{\\\"text\\\":\\\" $volume%\\\"}\"\n","// -*- mode: json -*-\n\n{\n\t\"layer\": \"top\",\n\t\"position\": \"top\",\n\n\t\"modules-left\": [\n\t\t\"sway/workspaces\",\n\t\t\"idle_inhibitor\",\n\t],\n\t\"modules-center\": [\n\t\t\"sway/window\",\n\t\t\"clock\",\n\t\t\"custom/volume\",\n    ],\n\n\t\"modules-right\": [\n\t\t\"custom/spotify\",\n\t\t\"memory\",\n\t\t\"cpu\",\n\t\t\"temperature\",\n\t\t\"disk\",\n\t\t\"custom/pacman\",\n\t\t\"custom/keyboard-layout\",\n\t\t\"custom/notification\",\n\t\t\"tray\",\n\t],\n\n\n\t\"sway/workspaces\": {\n\t\t\"disable-scroll\": false,\n\t\t\"format\": \"{name}\"\n\t},\n\n\n\t \"custom/spotify\": {\n    \t \"exec\": \"/usr/bin/python3 /home/tommi/.config/waybar/scripts/mediaplayer.py --player spotify\",\n     \t \"format\": \"{}  \",\n    \t \"return-type\": \"json\",\n    \t \"on-click\": \"playerctl play-pause\",\n    \t \"on-scroll-up\": \"playerctl next\",\n    \t \"on-scroll-down\": \"playerctl previous\"\n\t},\n\n\t\"custom/notification\": {\n        \"tooltip\": false,\n        \"format\": \"{} {icon}\",\n        \"format-icons\": {\n            \"notification\": \"\u003cbig\u003e\u003c/big\u003e\",\n            \"none\": \"\u003cbig\u003e\u003c/big\u003e\",\n            \"dnd-notification\": \"\u003cbig\u003e\u003c/big\u003e\",\n            \"dnd-none\": \"\u003cbig\u003e\u003c/big\u003e\"\n        },\n        \"return-type\": \"json\",\n        \"exec-if\": \"which swaync-client\",\n        \"exec\": \"swaync-client -swb\",\n        \"on-click\": \"swaync-client -t -sw\",\n        \"on-click-right\": \"swaync-client -d -sw\",\n        \"escape\": true\n    },\n\n\t\t\"custom/pipewire\": {\n    \t\"format\": \"{icon}\",\n    \t\"return-type\": \"json\",\n    \t\"signal\": 8,\n    \t\"interval\": \"once\",\n    \t\"format-icons\": {\n        \"mute\": \"\",\n        \"default\": [\"\", \"\", \"\", \"\"],\n    },\n    \"exec\": \"pw-volume status\"\n},\n\n\n\t\"clock\": {\n\t\t\"format\": \"{:%a. %d | %H:%M}\",\n\t\t\"tooltip\": false,\n\t\t\"on-click\": \"zim 'Tu Wiki' Journal:$(date +%Y):Week_$(date +%V)\",\n\t\t\"on-click-right\": \"zim 'Universidad' Journal:$(date +%Y):Week_$(date +%V)\"\n\t},\n\t\"custom/mpd-vol\": {\n\t\t\"interval\": 5,\n\t\t\"format\": \" {}\",\n\t\t\"exec\": \"mpc volume | tr -dc '0-9%'\",\n\t\t\"on-scroll-up\": \"mpc volume +10\",\n\t\t\"on-scroll-down\": \"mpc volume -10\"\n\t},\n\t\"pulseaudio\": {\n\t\t\"format\": \"{icon} {volume:2}% {format_source}\",\n\t\t\"format-bluetooth\": \"{icon}  {volume}%\",\n\t\t\"format-muted\": \"MUTE\",\n\t\t\"format-source\": \"  {volume}%\",\n\t\t\"format-source-muted\": \" \",\n\t\t\"format-icons\": {\n\t\t\t\"headphones\": \"\",\n\t\t\t\"default\": [\n\t\t\t\t\"\",\n\t\t\t\t\"\",\n\t\t\t\t\"\"\n\t\t\t]\n\t\t},\n\t\t\"scroll-step\": 5,\n\t\t\"on-click-right\": \"amixer set Capture toggle\",\n\t\t\"on-click\": \"pavucontrol\"\n\t},\n\t\"memory\": {\n\t\t\"interval\": 5,\n\t\t\"format\": \" {}%\",\n\t\t\"on-click\": \"$TERM -e htop\"\n\t},\n\t\"cpu\": {\n\t\t\"interval\": 5,\n        \"format\": \" {usage}%\",\n\t\t\"on-click\": \"$TERM -e htop\"\n\t},\n    \"temperature\": {\n        \"critical-threshold\": 75,\n        \"format\": \" {temperatureC}°C\"\n    },\n\t\"battery\": {\n\t\t\"states\": {\n\t\t\t\"good\": 95,\n\t\t\t\"warning\": 30,\n\t\t\t\"critical\": 15\n\t\t},\n\t\t\"format\": \"{icon} {capacity}%\",\n\t\t\"format-icons\": [\n\t\t\t\"\",\n\t\t\t\"\",\n\t\t\t\"\",\n\t\t\t\"\",\n\t\t\t\"\"\n\t\t]\n\t},\n\t\"disk\": {\n\t\t\"interval\": 5,\n\t\t\"format\": \" {percentage_used}%\",\n\t\t\"path\": \"/\",\n\t\t\"on-click\": \"dolphin\"\n\t},\n\t\"custom/pacman\": {\n\t\t\"format\": \" {}\",\n\t\t\"interval\": 3600, // every hour\n\t\t\"exec\": \"checkupdates | wc -l\", // # of updates\n\t\t\"exec-if\": \"exit 0\", // always run; consider advanced run conditions\n\t\t\"on-click\": \"$TERM -e up; pkill -SIGRTMIN+8 waybar\", // update system\n\t\t\"signal\": 8,\n\t},\n\t\"tray\": {\n\t\t\"icon-size\": 20,\n\t\t\"spacing\": 10\n\t},\n        \"custom/power\": {\n      \t        \"format\":\"⏻\",\n       \t        \"on-click\": \"nwg-bar\",\n      \t        \"tooltip\": false,\n        },\n        \"custom/keyboard-layout\": {\n      \t       \"exec\": \"swaymsg -t get_inputs | grep -m1 'xkb_active_layout_name' | cut -d '\\\"' -f4\",\n      \t       // Interval set only as a fallback, as the value is updated by signal\n      \t       \"interval\": 30,\n      \t       \"format\": \"  {}\", // Icon: keyboard\n      \t       // Signal sent by Sway key binding (~/.config/sway/key-bindings)\n      \t       \"signal\": 1, // SIGHUP\n      \t       \"tooltip\": false,\n               \"on-click\": \"~/.config/waybar/scripts/keyhint.sh\",\n},\n       \"custom/launcher\": {\n    \t       \"format\":\" \",\n    \t       \"on-click\": \"exec nwg-drawer -c 7 -is 70 -spacing 23\",\n    \t       \"tooltip\": false,\n},\n\n       \"type\": \"custom/cider-waybar\",\n       \"settings\": {}\n},\n\n\n      \"idle_inhibitor\": {\n           \"format\": \"{icon}\",\n           \"format-icons\": {\n              \"activated\": \"\",\n              \"deactivated\": \"\",\n        }\n},\n    \"custom/exit\": {\n\t\t\"tooltip\": false,\n\t\t\"format\": \"⏻\",\n\t\t\"on-click\": \"swaymsg exit\",\n\t\t\"on-click-right\": \"systemctl poweroff\",\n\t\t\"on-click-middle\": \"systemctl reboot\"\n\t}\n}\n\n{\n    \"custom/volume\": {\n        \"exec\": \"/home/tommi/.config/waybar/scripts/volume_percent.sh\",\n        \"return-type\": \"json\",\n        \"interval\": 1\n    }\n  }\n}\n\n","\n","{\n    \"custom/volume\": {\n        \"exec\": \"/home/tommi/.config/waybar/scripts/volume_percent.sh\",\n        \"return-type\": \"json\",\n        \"interval\": 1\n    }\n}\n","// -*- mode: json -*-\n\n{\n\t\"layer\": \"top\",\n\t\"position\": \"top\",\n\n\t\"modules-left\": [\n\t\t\"sway/workspaces\",\n\t\t\"idle_inhibitor\",\n\t],\n\t\"modules-center\": [\n\t\t\"sway/window\",\n\t\t\"clock\",\n\t\t\"custom/volume\",\n    ],\n\n\t\"modules-right\": [\n\t\t\"custom/spotify\",\n\t\t\"memory\",\n\t\t\"cpu\",\n\t\t\"temperature\",\n\t\t\"disk\",\n\t\t\"custom/pacman\",\n\t\t\"custom/keyboard-layout\",\n\t\t\"custom/notification\",\n\t\t\"tray\",\n\t],\n\n\n\t\"sway/workspaces\": {\n\t\t\"disable-scroll\": false,\n\t\t\"format\": \"{name}\"\n\t},\n\n\n\t \"custom/spotify\": {\n    \t \"exec\": \"/usr/bin/python3 /home/tommi/.config/waybar/scripts/mediaplayer.py --player spotify\",\n     \t \"format\": \"{}  \",\n    \t \"return-type\": \"json\",\n    \t \"on-click\": \"playerctl play-pause\",\n    \t \"on-scroll-up\": \"playerctl next\",\n    \t \"on-scroll-down\": \"playerctl previous\"\n\t},\n\n\t\"custom/notification\": {\n        \"tooltip\": false,\n        \"format\": \"{} {icon}\",\n        \"format-icons\": {\n            \"notification\": \"\u003cbig\u003e\u003c/big\u003e\",\n            \"none\": \"\u003cbig\u003e\u003c/big\u003e\",\n            \"dnd-notification\": \"\u003cbig\u003e\u003c/big\u003e\",\n            \"dnd-none\": \"\u003cbig\u003e\u003c/big\u003e\"\n        },\n        \"return-type\": \"json\",\n        \"exec-if\": \"which swaync-client\",\n        \"exec\": \"swaync-client -swb\",\n        \"on-click\": \"swaync-client -t -sw\",\n        \"on-click-right\": \"swaync-client -d -sw\",\n        \"escape\": true\n    },\n\n\t\t\"custom/pipewire\": {\n    \t\"format\": \"{icon}\",\n    \t\"return-type\": \"json\",\n    \t\"signal\": 8,\n    \t\"interval\": \"once\",\n    \t\"format-icons\": {\n        \"mute\": \"\",\n        \"default\": [\"\", \"\", \"\", \"\"],\n    },\n    \"exec\": \"pw-volume status\"\n},\n\n\n\t\"clock\": {\n\t\t\"format\": \"{:%a. %d | %H:%M}\",\n\t\t\"tooltip\": false,\n\t\t\"on-click\": \"zim 'Tu Wiki' Journal:$(date +%Y):Week_$(date +%V)\",\n\t\t\"on-click-right\": \"zim 'Universidad' Journal:$(date +%Y):Week_$(date +%V)\"\n\t},\n\t\"custom/mpd-vol\": {\n\t\t\"interval\": 5,\n\t\t\"format\": \" {}\",\n\t\t\"exec\": \"mpc volume | tr -dc '0-9%'\",\n\t\t\"on-scroll-up\": \"mpc volume +10\",\n\t\t\"on-scroll-down\": \"mpc volume -10\"\n\t},\n\t\"pulseaudio\": {\n\t\t\"format\": \"{icon} {volume:2}% {format_source}\",\n\t\t\"format-bluetooth\": \"{icon}  {volume}%\",\n\t\t\"format-muted\": \"MUTE\",\n\t\t\"format-source\": \"  {volume}%\",\n\t\t\"format-source-muted\": \" \",\n\t\t\"format-icons\": {\n\t\t\t\"headphones\": \"\",\n\t\t\t\"default\": [\n\t\t\t\t\"\",\n\t\t\t\t\"\",\n\t\t\t\t\"\"\n\t\t\t]\n\t\t},\n\t\t\"scroll-step\": 5,\n\t\t\"on-click-right\": \"amixer set Capture toggle\",\n\t\t\"on-click\": \"pavucontrol\"\n\t},\n\t\"memory\": {\n\t\t\"interval\": 5,\n\t\t\"format\": \" {}%\",\n\t\t\"on-click\": \"$TERM -e htop\"\n\t},\n\t\"cpu\": {\n\t\t\"interval\": 5,\n        \"format\": \" {usage}%\",\n\t\t\"on-click\": \"$TERM -e htop\"\n\t},\n    \"temperature\": {\n        \"critical-threshold\": 75,\n        \"format\": \" {temperatureC}°C\"\n    },\n\t\"battery\": {\n\t\t\"states\": {\n\t\t\t\"good\": 95,\n\t\t\t\"warning\": 30,\n\t\t\t\"critical\": 15\n\t\t},\n\t\t\"format\": \"{icon} {capacity}%\",\n\t\t\"format-icons\": [\n\t\t\t\"\",\n\t\t\t\"\",\n\t\t\t\"\",\n\t\t\t\"\",\n\t\t\t\"\"\n\t\t]\n\t},\n\t\"disk\": {\n\t\t\"interval\": 5,\n\t\t\"format\": \" {percentage_used}%\",\n\t\t\"path\": \"/\",\n\t\t\"on-click\": \"dolphin\"\n\t},\n\t\"custom/pacman\": {\n\t\t\"format\": \" {}\",\n\t\t\"interval\": 3600, // every hour\n\t\t\"exec\": \"checkupdates | wc -l\", // # of updates\n\t\t\"exec-if\": \"exit 0\", // always run; consider advanced run conditions\n\t\t\"on-click\": \"$TERM -e up; pkill -SIGRTMIN+8 waybar\", // update system\n\t\t\"signal\": 8,\n\t},\n\t\"tray\": {\n\t\t\"icon-size\": 20,\n\t\t\"spacing\": 10\n\t},\n        \"custom/power\": {\n      \t        \"format\":\"⏻\",\n       \t        \"on-click\": \"nwg-bar\",\n      \t        \"tooltip\": false,\n        },\n        \"custom/keyboard-layout\": {\n      \t       \"exec\": \"swaymsg -t get_inputs | grep -m1 'xkb_active_layout_name' | cut -d '\\\"' -f4\",\n      \t       // Interval set only as a fallback, as the value is updated by signal\n      \t       \"interval\": 30,\n      \t       \"format\": \"  {}\", // Icon: keyboard\n      \t       // Signal sent by Sway key binding (~/.config/sway/key-bindings)\n      \t       \"signal\": 1, // SIGHUP\n      \t       \"tooltip\": false,\n               \"on-click\": \"~/.config/waybar/scripts/keyhint.sh\",\n},\n       \"custom/launcher\": {\n    \t       \"format\":\" \",\n    \t       \"on-click\": \"exec nwg-drawer -c 7 -is 70 -spacing 23\",\n    \t       \"tooltip\": false,\n},\n\n       \"type\": \"custom/cider-waybar\",\n       \"settings\": {}\n},\n\n\n      \"idle_inhibitor\": {\n           \"format\": \"{icon}\",\n           \"format-icons\": {\n              \"activated\": \"\",\n              \"deactivated\": \"\",\n        }\n},\n    \"custom/exit\": {\n\t\t\"tooltip\": false,\n\t\t\"format\": \"⏻\",\n\t\t\"on-click\": \"swaymsg exit\",\n\t\t\"on-click-right\": \"systemctl poweroff\",\n\t\t\"on-click-middle\": \"systemctl reboot\"\n\t}\n}\n\n{\n    \"custom/volume\": {\n        \"exec\": \"/home/tommi/.config/waybar/scripts/volume_percent.sh\",\n        \"return-type\": \"json\",\n        \"interval\": 1\n    }\n\n}\n","sudo dnf install fastfetch","\"pulseaudio\": {\n\t\t\"format\": \"{icon} {volume:2}% {format_source}\",\n\t\t\"format-bluetooth\": \"{icon}  {volume}%\",\n\t\t\"format-muted\": \"MUTE\",\n\t\t\"format-source\": \"  {volume}%\",\n\t\t\"format-source-muted\": \" \",\n\t\t\"format-icons\": {\n\t\t\t\"headphones\": \"\",\n\t\t\t\"default\": [\n\t\t\t\t\"\",\n\t\t\t\t\"\",\n\t\t\t\t\"\"\n\t\t\t]\n\t\t},","https://github.com/Alexays/Waybar/wiki/Module:-PulseAudio","\"on-scroll-up\": \"pactl set-sink-volume @DEFAULT_SINK@ +5%\",\n    \"on-scroll-down\": \"pactl set-sink-volume @DEFAULT_SINK@ -5%\",","git clone https://github.com/TheDarkBug/uwufetch.git\n","git clone https://github.com/ChrisTitusTech/Top-5-Bootloader-Themes","sudo hostnamectl set-hostname --pretty \"Emily's 2nd dev laptop\"\n","sudo hostnamectl set-hostname --static emily-dev-2\n","\"pulseaudio\": {\n\t\t\"format\": \"{icon} {volume:2}% {format_source}\",\n\t\t\"format-bluetooth\": \"{icon}  {volume}%\",\n\t\t\"format-muted\": \"MUTE\",\n\t\t\"format-source\": \"  {volume}%\",\n\t\t\"format-source-muted\": \" \",\n\t\t\"on-scroll-up\": \"pactl set-sink-volume @DEFAULT_SINK@ +5%\",\n    \t\"on-scroll-down\": \"pactl set-sink-volume @DEFAULT_SINK@ -5%\",\n\t\t\"format-icons\": {\n\t\t\t\"headphones\": \"\",\n\t\t\t\"default\": [\n\t\t\t\t\"\",\n\t\t\t\t\"\",\n\t\t\t\t\"\"\n\t\t\t]\n\t\t},","/home/tommi/.config\n/home/tommi/.icons\n/home/tommi/.local"]